rcognita/ROS_harnesses.py
rcognita/_Plugins__fake_file_config_source.py
rcognita/__fake_config_loader_impl.py
rcognita/__fake_plugins.py
rcognita/__init__.py
rcognita/__instantiate.py
rcognita/__obstacles_parser.py
rcognita/__utilities.py
rcognita/__w_plotting.py
rcognita/actors.py
rcognita/callbacks.py
rcognita/controllers.py
rcognita/critics.py
rcognita/loggers.py
rcognita/models.py
rcognita/objectives.py
rcognita/observers.py
rcognita/optimizers.py
rcognita/predictors.py
rcognita/scenarios.py
rcognita/simulator.py
rcognita/solvers.py
rcognita/systems.py
rcognita/visualization/__init__.py
rcognita/visualization/animator.py
rcognita/visualization/vis_2tank.py
rcognita/visualization/vis_3wrobot.py
rcognita/visualization/vis_grid_world.py
rcognita/visualization/vis_inverted_pendulum.py
tests/__init__.py
tests/presets/2tank.py
tests/presets/__init__.py
rcognita-0.2.1.dist-info/LICENSE
rcognita-0.2.1.dist-info/METADATA
rcognita-0.2.1.dist-info/WHEEL
rcognita-0.2.1.dist-info/top_level.txt
rcognita-0.2.1.dist-info/RECORD
