Metadata-Version: 2.1
Name: rcognita
Version: 0.2.1
Summary: rcognita is a framework for hybrid agent-environment loop simulation, with a library of predictive and stabilizing reinforcement learning setups
Home-page: https://gitflic.ru/project/aidynamicaction/rcognita
Author: AIDynamicAction
Classifier: Programming Language :: Python :: 3
Classifier: Operating System :: OS Independent
Requires-Python: >=3.6
License-File: LICENSE
Requires-Dist: matplotlib (>=3.1.3)
Requires-Dist: mpldatacursor-rcognita (==0.7.2)
Requires-Dist: numpy (>=1.20.1)
Requires-Dist: scipy (>=1.5.0)
Requires-Dist: svgpath2mpl (==0.2.1)
Requires-Dist: tabulate (>=0.8.7)
Requires-Dist: systems (==0.1.0)
Requires-Dist: shapely (==1.7.1)
Requires-Dist: tabulate (==0.8.7)
Requires-Dist: recursive-monkey-patch (==0.4.0)
Requires-Dist: omegaconf (>=2.3.0)
Requires-Dist: hydra-core (>=1.3.1)
Provides-Extra: casadi
Requires-Dist: casadi (>=3.5.5) ; extra == 'casadi'
Provides-Extra: sippy
Requires-Dist: sippy-rcognita (==0.2.1) ; extra == 'sippy'
Provides-Extra: torch
Requires-Dist: torch (>=1.12.1) ; extra == 'torch'
